githubapp/CreateEvent.py
githubapp/Event.py
githubapp/GithubApp.py
githubapp/IssueCommentEvent.py
githubapp/LazyCompletableGithubObject.py
githubapp/ReleaseEvent.py
githubapp/__init__.py
githubapp/handlers/__init__.py
githubapp/handlers/exceptions.py
githubapp/handlers/handler.py
githubapp/handlers/flask/__init__.py
githubapp/handlers/flask/flask_handler.py
GithubAppHandler-0.0.4.dist-info/LICENSE
GithubAppHandler-0.0.4.dist-info/METADATA
GithubAppHandler-0.0.4.dist-info/WHEEL
GithubAppHandler-0.0.4.dist-info/top_level.txt
GithubAppHandler-0.0.4.dist-info/RECORD
