Metadata-Version: 2.1
Name: GithubAppHandler
Version: 0.0.4
Summary: Package to help creates Github Apps.
Author: Heitor Luis Polidoro
License: MIT
Project-URL: Homepage, https://github.com/heitorpolidoro/PyGithubApp
Keywords: github,app,githubapp
Classifier: Programming Language :: Python :: 3
Classifier: License :: OSI Approved :: MIT License
Classifier: Operating System :: OS Independent
Requires-Python: >=3.9
License-File: LICENSE
Requires-Dist: Polidoro-PyGithub ==2.2.0rc5
Provides-Extra: flask
Requires-Dist: flask ; extra == 'flask'
